eventkit/__init__.py
eventkit/event.py
eventkit/util.py
eventkit/version.py
eventkit/ops/__init__.py
eventkit/ops/aggregate.py
eventkit/ops/array.py
eventkit/ops/combine.py
eventkit/ops/create.py
eventkit/ops/misc.py
eventkit/ops/op.py
eventkit/ops/select.py
eventkit/ops/timing.py
eventkit/ops/transform.py
tests/__init__.py
tests/aggregate_test.py
tests/combine_test.py
tests/create_test.py
tests/event_test.py
tests/select_test.py
tests/timing_test.py
tests/transform_test.py
eventkit-1.0.3.dist-info/LICENSE
eventkit-1.0.3.dist-info/METADATA
eventkit-1.0.3.dist-info/WHEEL
eventkit-1.0.3.dist-info/top_level.txt
eventkit-1.0.3.dist-info/RECORD
