Metadata-Version: 2.1
Name: eventkit
Version: 1.0.3
Summary: Event-driven data pipelines
Home-page: https://github.com/erdewit/eventkit
Author: Ewald R. de Wit
Author-email: ewald.de.wit@gmail.com
License: BSD
Keywords: python asyncio event driven data pipelines
Classifier: Development Status :: 4 - Beta
Classifier: Intended Audience :: Science/Research
Classifier: Intended Audience :: Developers
Classifier: License :: OSI Approved :: BSD License
Classifier: Programming Language :: Python :: 3.6
Classifier: Programming Language :: Python :: 3.7
Classifier: Programming Language :: Python :: 3.8
Classifier: Programming Language :: Python :: 3.9
Classifier: Programming Language :: Python :: 3.10
Classifier: Programming Language :: Python :: 3.11
Classifier: Programming Language :: Python :: 3.12
Classifier: Programming Language :: Python :: 3 :: Only
License-File: LICENSE
